{
  "scopes": [
    {
      "key": "common-transit-convention-traders",
      "name": "Common Transit Convention Traders",
      "description": "Common Transit Convention Traders Public API"
    }
  ],
  "api": {
    "name": "CTC Traders",
    "description": "The public API to allow traders to submit and receive Common Transit Convention (IE) messages",
    "context": "customs/transits",
    "categories": ["CUSTOMS"],
    "versions": [
      {
        "version": "1.0",
        "status": "STABLE",
        "endpointsEnabled": true,
        "access": {
          "type": "PUBLIC"
        },
        "fieldDefinitions": [{
          "name": "notificationUrl",
          "shortDescription": "Notification URL",
          "description": "What is your notification web address for us to send push notifications to?",
          "type": "PPNSField",
          "hint": "You must only give us a web address that you own. Your application will use this address to listen to notifications from HMRC.",
          "validation": {
            "errorMessage": "notificationUrl must be a valid https URL",
            "rules": [
              {
                "UrlValidationRule": {}
              },
              {
                "RegexValidationRule": {
                  "regex" : "^https.*"
                }
              }
            ]
          }
        }]
      },
      {
        "version": "2.0",
        "status": "BETA",
        "endpointsEnabled": true,
        "access": {
          "type": "PUBLIC"
        },
        "fieldDefinitions": [{
          "name": "notificationUrl",
          "shortDescription": "Notification URL",
          "description": "What is your notification web address for us to send push notifications to?",
          "type": "PPNSField",
          "hint": "You must only give us a web address that you own. Your application will use this address to listen to notifications from HMRC.",
          "validation": {
            "errorMessage": "notificationUrl must be a valid https URL",
            "rules": [
              {
                "UrlValidationRule": {}
              },
              {
                "RegexValidationRule": {
                  "regex" : "^https.*"
                }
              }
            ]
          }
        }]
      },
      {
        "version": "2.1",
        "status": "ALPHA",
        "endpointsEnabled": true,
        "access": {
          "type": "PUBLIC"
        },
        "fieldDefinitions": [{
          "name": "notificationUrl",
          "shortDescription": "Notification URL",
          "description": "What is your notification web address for us to send push notifications to?",
          "type": "PPNSField",
          "hint": "You must only give us a web address that you own. Your application will use this address to listen to notifications from HMRC.",
          "validation": {
            "errorMessage": "notificationUrl must be a valid https URL",
            "rules": [
              {
                "UrlValidationRule": {}
              },
              {
                "RegexValidationRule": {
                  "regex" : "^https.*"
                }
              }
            ]
          }
        }]
      }
    ]
  }
}
